sphinx_graphql/__init__.py
sphinx_graphql/_version_git.py
sphinx_graphql/attachGraphiQL.js
sphinx_graphql/graphiql.py
sphinx_graphql-0.1.2.dist-info/LICENSE
sphinx_graphql-0.1.2.dist-info/METADATA
sphinx_graphql-0.1.2.dist-info/WHEEL
sphinx_graphql-0.1.2.dist-info/top_level.txt
sphinx_graphql-0.1.2.dist-info/RECORD
