Metadata-Version: 2.1
Name: sphinx-graphql
Version: 0.1.2
Summary: Sphinx utilities for documenting GraphQL APIs
Home-page: https://github.com/dls-controls/sphinx-graphql
Author: Tom Cobb, Callum Forrester
Author-email: tom.cobb@diamond.ac.uk, callum.forrester@diamond.ac.uk
License: Apache License 2.0
Platform: UNKNOWN
Classifier: Development Status :: 4 - Beta
Classifier: License :: OSI Approved :: Apache Software License
Classifier: Programming Language :: Python :: 3.7
Classifier: Programming Language :: Python :: 3.8
Classifier: Programming Language :: Python :: 3.9
License-File: LICENSE
Requires-Dist: sphinx
